[{"__type__":"cc.SpriteFrame","content":{"name":"win5","texture":"c9a6e40c-b7c0-4ed8-ba51-eb261d82e791","rect":[1795,200,169,129],"offset":[-11,-15],"originalSize":[449,271]}},{"__type__":"cc.SpriteFrame","content":{"name":"win0","texture":"c9a6e40c-b7c0-4ed8-ba51-eb261d82e791","rect":[1344,2,449,271],"offset":[0,0],"originalSize":[449,271]}},{"__type__":"cc.SpriteFrame","content":{"name":"win1","texture":"c9a6e40c-b7c0-4ed8-ba51-eb261d82e791","rect":[1344,275,383,157],"offset":[3,-24],"originalSize":[449,271]}},{"__type__":"cc.SpriteFrame","content":{"name":"win8","texture":"c9a6e40c-b7c0-4ed8-ba51-eb261d82e791","rect":[1634,434,87,125],"offset":[146,-15],"originalSize":[449,271]}},{"__type__":"cc.SpriteFrame","content":{"name":"win10","texture":"c9a6e40c-b7c0-4ed8-ba51-eb261d82e791","rect":[2,2,1340,1080],"offset":[22,0],"originalSize":[1492,1200]}},{"__type__":"cc.SpriteFrame","content":{"name":"win4","texture":"c9a6e40c-b7c0-4ed8-ba51-eb261d82e791","rect":[1729,331,169,127],"offset":[-76,-14],"originalSize":[449,271]}},{"__type__":"cc.SpriteAtlas","_name":"Animas-win.plist","_spriteFrames":{"win0":{"__uuid__":"6610b65a-6250-43e9-842a-8b6fbb86ca72"},"win1":{"__uuid__":"7ce1fff3-6fc3-4f80-a277-6e155e6722be"},"win10":{"__uuid__":"9a121b20-4a8b-448c-a57d-5ac50dfd259d"},"win2":{"__uuid__":"cee133d0-4beb-47ec-a290-4466e34f1032"},"win3":{"__uuid__":"ff7cbe8e-7d85-4539-82b7-ca6fbf359fe9"},"win4":{"__uuid__":"a04ab48b-d197-4963-9151-cf3c63f76d5a"},"win5":{"__uuid__":"441cf354-54a7-4ad4-aa60-3d0eefa72136"},"win6":{"__uuid__":"fdb9d88e-093f-4ee8-87ce-61c7e5657fd5"},"win7":{"__uuid__":"b909c506-118e-481b-a8ee-d13db7706064"},"win8":{"__uuid__":"92f42e06-36bd-4d37-af10-b6765da9a155"},"win9":{"__uuid__":"c9dbe99c-ab9e-4012-b8bc-575a65e7e477"}}},{"__type__":"cc.SpriteFrame","content":{"name":"win7","texture":"c9a6e40c-b7c0-4ed8-ba51-eb261d82e791","rect":[1344,434,159,127],"offset":[110,-16],"originalSize":[449,271]}},{"__type__":"cc.SpriteFrame","content":{"name":"win9","texture":"c9a6e40c-b7c0-4ed8-ba51-eb261d82e791","rect":[1795,2,196,204],"offset":[-20,-16],"originalSize":[266,256],"rotated":1}},{"__type__":"cc.SpriteFrame","content":{"name":"win2","texture":"c9a6e40c-b7c0-4ed8-ba51-eb261d82e791","rect":[1723,460,83,127],"offset":[-141,-14],"originalSize":[449,271],"rotated":1}},{"__type__":"cc.SpriteFrame","content":{"name":"win6","texture":"c9a6e40c-b7c0-4ed8-ba51-eb261d82e791","rect":[1900,331,143,129],"offset":[50,-15],"originalSize":[449,271]}},{"__type__":"cc.SpriteFrame","content":{"name":"win3","texture":"c9a6e40c-b7c0-4ed8-ba51-eb261d82e791","rect":[1505,434,127,127],"offset":[-119,-14],"originalSize":[449,271]}}]